{
  "app": [
    {
      "definition": {
        "appV2": {
          "type": "front-end",
          "id": "05231ff7-bfc1-4f9f-a090-0f0b4b69007b",
          "name": "app6",
          "slug": "05231ff7-bfc1-4f9f-a090-0f0b4b69007b",
          "isPublic": null,
          "isMaintenanceOn": false,
          "icon": "sentfast",
          "organizationId": "56509beb-a5fa-4361-be3b-acec5ce23a82",
          "currentVersionId": null,
          "userId": "b07938da-9cf1-49ee-9dc3-e363f7c66249",
          "workflowApiToken": null,
          "workflowEnabled": false,
          "createdAt": "2025-02-04T07:08:48.765Z",
          "creationMode": "DEFAULT",
          "updatedAt": "2025-02-04T07:08:48.765Z",
          "editingVersion": {
            "id": "3384fe53-aee5-41b5-9364-babe0ff4d4b7",
            "name": "v2",
            "definition": null,
            "globalSettings": {
              "hideHeader": false,
              "appInMaintenance": false,
              "canvasMaxWidth": 100,
              "canvasMaxWidthType": "%",
              "canvasMaxHeight": 2400,
              "canvasBackgroundColor": "#edeff5",
              "backgroundFxQuery": "",
              "appMode": "auto"
            },
            "pageSettings": null,
            "showViewerNavigation": true,
            "homePageId": "f105fe36-3d79-4102-bb21-629726a2f19c",
            "appId": "05231ff7-bfc1-4f9f-a090-0f0b4b69007b",
            "currentEnvironmentId": "e8aa3de4-7f32-4e5b-9624-3e8c8dc6f7e3",
            "promotedFrom": null,
            "createdAt": "2025-02-04T07:10:15.175Z",
            "updatedAt": "2025-02-04T07:10:15.159Z"
          },
          "components": [
            {
              "id": "fb02dc02-cba3-43f2-9785-379f1381b612",
              "name": "listview1",
              "type": "Listview",
              "pageId": "f105fe36-3d79-4102-bb21-629726a2f19c",
              "parent": null,
              "properties": {
                "data": {
                  "value": "{{[\n    { imageURL: 'https://www.svgrepo.com/show/34217/image.svg', text: 'Sample text 1', buttonText: 'Button 1' },\n      { imageURL: 'https://www.svgrepo.com/show/34217/image.svg', text: 'Sample text 1', buttonText: 'Button 2' },\n      { imageURL: 'https://www.svgrepo.com/show/34217/image.svg', text: 'Sample text 1', buttonText: 'Button 3' },\n    ]}}"
                },
                "mode": {
                  "value": "list"
                },
                "columns": {
                  "value": "{{3}}"
                },
                "rowHeight": {
                  "value": "100"
                },
                "visible": {
                  "value": "{{true}}"
                },
                "showBorder": {
                  "value": "{{true}}"
                },
                "rowsPerPage": {
                  "value": "{{10}}"
                },
                "enablePagination": {
                  "value": "{{false}}"
                }
              },
              "general": {},
              "styles": {
                "backgroundColor": {
                  "value": "#fff"
                },
                "borderColor": {
                  "value": "#dadcde"
                },
                "visibility": {
                  "value": "{{true}}"
                },
                "disabledState": {
                  "value": "{{false}}"
                },
                "borderRadius": {
                  "value": "{{4}}"
                }
              },
              "generalStyles": {
                "boxShadow": {
                  "value": "0px 0px 0px 0px #00000040"
                }
              },
              "displayPreferences": {
                "showOnDesktop": {
                  "value": "{{true}}"
                },
                "showOnMobile": {
                  "value": "{{false}}"
                }
              },
              "validation": {},
              "createdAt": "2025-02-04T07:10:15.159Z",
              "updatedAt": "2025-02-04T07:10:15.159Z",
              "layouts": [
                {
                  "id": "7118eef1-1131-4d7d-b1a4-8f4d62825405",
                  "type": "desktop",
                  "top": 90,
                  "left": 3,
                  "width": 30,
                  "height": 300,
                  "componentId": "fb02dc02-cba3-43f2-9785-379f1381b612",
                  "dimensionUnit": "count",
                  "updatedAt": "2025-02-04T07:10:15.159Z"
                },
                {
                  "id": "2e77e9c0-2183-4d41-ae77-c48988852ff3",
                  "type": "mobile",
                  "top": 90,
                  "left": 3,
                  "width": 30,
                  "height": 300,
                  "componentId": "fb02dc02-cba3-43f2-9785-379f1381b612",
                  "dimensionUnit": "count",
                  "updatedAt": "2025-02-04T07:10:15.159Z"
                }
              ]
            },
            {
              "id": "8ab78578-5b6d-4f5f-864b-01bca9c534f9",
              "name": "image1",
              "type": "Image",
              "pageId": "f105fe36-3d79-4102-bb21-629726a2f19c",
              "parent": "fb02dc02-cba3-43f2-9785-379f1381b612",
              "properties": {
                "source": {
                  "value": "{{listItem.imageURL}}"
                },
                "visible": {
                  "value": "{{true}}"
                },
                "loadingState": {
                  "value": "{{false}}"
                },
                "alternativeText": {
                  "value": ""
                },
                "zoomButtons": {
                  "value": "{{false}}"
                },
                "rotateButton": {
                  "value": "{{false}}"
                }
              },
              "general": {},
              "styles": {
                "borderType": {
                  "value": "none"
                },
                "padding": {
                  "value": "0"
                },
                "visibility": {
                  "value": "{{true}}"
                },
                "disabledState": {
                  "value": "{{false}}"
                },
                "imageFit": {
                  "value": "contain"
                },
                "backgroundColor": {
                  "value": ""
                }
              },
              "generalStyles": {
                "boxShadow": {
                  "value": "0px 0px 0px 0px #00000040"
                }
              },
              "displayPreferences": {
                "showOnDesktop": {
                  "value": "{{true}}"
                },
                "showOnMobile": {
                  "value": "{{false}}"
                }
              },
              "validation": {},
              "createdAt": "2025-02-04T07:10:15.159Z",
              "updatedAt": "2025-02-04T07:10:15.159Z",
              "layouts": [
                {
                  "id": "02e8ec18-7c1d-4a9b-ac60-c5a03ad09468",
                  "type": "desktop",
                  "top": 15,
                  "left": 3,
                  "width": 6.976744186046512,
                  "height": 100,
                  "componentId": "8ab78578-5b6d-4f5f-864b-01bca9c534f9",
                  "dimensionUnit": "count",
                  "updatedAt": "2025-02-04T07:10:15.159Z"
                },
                {
                  "id": "976d77c1-77e2-44ed-b119-f6a8f86422a0",
                  "type": "mobile",
                  "top": 15,
                  "left": 3,
                  "width": 6.976744186046512,
                  "height": 100,
                  "componentId": "8ab78578-5b6d-4f5f-864b-01bca9c534f9",
                  "dimensionUnit": "count",
                  "updatedAt": "2025-02-04T07:10:15.159Z"
                }
              ]
            },
            {
              "id": "e329c3ad-0bfa-46f9-b15e-11fbedd5ab74",
              "name": "text1",
              "type": "Text",
              "pageId": "f105fe36-3d79-4102-bb21-629726a2f19c",
              "parent": "fb02dc02-cba3-43f2-9785-379f1381b612",
              "properties": {
                "textFormat": {
                  "value": "html"
                },
                "text": {
                  "value": "{{listItem.text}}"
                },
                "loadingState": {
                  "value": "{{false}}"
                },
                "disabledState": {
                  "value": "{{false}}"
                },
                "visibility": {
                  "value": "{{true}}"
                }
              },
              "general": {},
              "styles": {
                "backgroundColor": {
                  "value": "#fff00000"
                },
                "textColor": {
                  "value": "#000000"
                },
                "textSize": {
                  "value": "{{14}}"
                },
                "textAlign": {
                  "value": "left"
                },
                "fontWeight": {
                  "value": "normal"
                },
                "decoration": {
                  "value": "none"
                },
                "transformation": {
                  "value": "none"
                },
                "fontStyle": {
                  "value": "normal"
                },
                "lineHeight": {
                  "value": "{{1.5}}"
                },
                "textIndent": {
                  "value": "{{0}}"
                },
                "letterSpacing": {
                  "value": "{{0}}"
                },
                "wordSpacing": {
                  "value": "{{0}}"
                },
                "fontVariant": {
                  "value": "normal"
                },
                "verticalAlignment": {
                  "value": "center"
                },
                "padding": {
                  "value": "default"
                },
                "boxShadow": {
                  "value": "0px 0px 0px 0px #00000090"
                },
                "borderColor": {
                  "value": ""
                },
                "borderRadius": {
                  "value": "{{6}}"
                },
                "isScrollRequired": {
                  "value": "enabled"
                }
              },
              "generalStyles": {
                "boxShadow": {
                  "value": "0px 0px 0px 0px #00000040"
                }
              },
              "displayPreferences": {
                "showOnDesktop": {
                  "value": "{{true}}"
                },
                "showOnMobile": {
                  "value": "{{false}}"
                }
              },
              "validation": {},
              "createdAt": "2025-02-04T07:10:15.159Z",
              "updatedAt": "2025-02-04T07:10:15.159Z",
              "layouts": [
                {
                  "id": "403310d3-6f95-4058-8e42-8388c8c693d2",
                  "type": "desktop",
                  "top": 50,
                  "left": 11,
                  "width": 13.953488372093023,
                  "height": 30,
                  "componentId": "e329c3ad-0bfa-46f9-b15e-11fbedd5ab74",
                  "dimensionUnit": "count",
                  "updatedAt": "2025-02-04T07:10:15.159Z"
                },
                {
                  "id": "105b7c7e-a264-4d3f-803f-b2593442b7d2",
                  "type": "mobile",
                  "top": 50,
                  "left": 11,
                  "width": 13.953488372093023,
                  "height": 30,
                  "componentId": "e329c3ad-0bfa-46f9-b15e-11fbedd5ab74",
                  "dimensionUnit": "count",
                  "updatedAt": "2025-02-04T07:10:15.159Z"
                }
              ]
            },
            {
              "id": "e72d25df-9d7a-4a4a-9a1f-792e382521b9",
              "name": "button1",
              "type": "Button",
              "pageId": "f105fe36-3d79-4102-bb21-629726a2f19c",
              "parent": "fb02dc02-cba3-43f2-9785-379f1381b612",
              "properties": {
                "text": {
                  "value": "{{listItem.buttonText}}"
                },
                "visibility": {
                  "value": "{{true}}"
                },
                "disabledState": {
                  "value": "{{false}}"
                },
                "loadingState": {
                  "value": "{{false}}"
                },
                "tooltip": {
                  "value": ""
                }
              },
              "general": {},
              "styles": {
                "textColor": {
                  "value": "#FFFFFF"
                },
                "borderColor": {
                  "value": "#4368E3"
                },
                "loaderColor": {
                  "value": "#FFFFFF"
                },
                "borderRadius": {
                  "value": "{{6}}"
                },
                "backgroundColor": {
                  "value": "#4368E3"
                },
                "iconColor": {
                  "value": "#FFFFFF"
                },
                "direction": {
                  "value": "left"
                },
                "padding": {
                  "value": "default"
                },
                "boxShadow": {
                  "value": "0px 0px 0px 0px #00000090"
                },
                "icon": {
                  "value": "IconAlignBoxBottomLeft"
                },
                "iconVisibility": {
                  "value": false
                },
                "type": {
                  "value": "primary"
                }
              },
              "generalStyles": {
                "boxShadow": {
                  "value": "0px 0px 0px 0px #00000040"
                }
              },
              "displayPreferences": {
                "showOnDesktop": {
                  "value": "{{true}}"
                },
                "showOnMobile": {
                  "value": "{{false}}"
                }
              },
              "validation": {},
              "createdAt": "2025-02-04T07:10:15.159Z",
              "updatedAt": "2025-02-04T07:10:15.159Z",
              "layouts": [
                {
                  "id": "20cf74a3-c880-4c11-9820-1a338711a6e4",
                  "type": "desktop",
                  "top": 50,
                  "left": 26,
                  "width": 18.6046511627907,
                  "height": 30,
                  "componentId": "e72d25df-9d7a-4a4a-9a1f-792e382521b9",
                  "dimensionUnit": "count",
                  "updatedAt": "2025-02-04T07:10:15.159Z"
                },
                {
                  "id": "c53da6b7-78b9-41b1-a9c9-f2bae207615c",
                  "type": "mobile",
                  "top": 50,
                  "left": 26,
                  "width": 18.6046511627907,
                  "height": 30,
                  "componentId": "e72d25df-9d7a-4a4a-9a1f-792e382521b9",
                  "dimensionUnit": "count",
                  "updatedAt": "2025-02-04T07:10:15.159Z"
                }
              ]
            }
          ],
          "pages": [
            {
              "id": "f105fe36-3d79-4102-bb21-629726a2f19c",
              "name": "Home",
              "handle": "home",
              "index": 1,
              "disabled": null,
              "hidden": null,
              "icon": null,
              "createdAt": "2025-02-04T07:10:15.159Z",
              "updatedAt": "2025-02-04T07:10:15.319Z",
              "autoComputeLayout": false,
              "appVersionId": "3384fe53-aee5-41b5-9364-babe0ff4d4b7",
              "pageGroupIndex": 1,
              "pageGroupId": null,
              "isPageGroup": false
            }
          ],
          "events": [],
          "dataQueries": [],
          "dataSources": [],
          "appVersions": [
            {
              "id": "3384fe53-aee5-41b5-9364-babe0ff4d4b7",
              "name": "v2",
              "definition": null,
              "globalSettings": {
                "hideHeader": false,
                "appInMaintenance": false,
                "canvasMaxWidth": 100,
                "canvasMaxWidthType": "%",
                "canvasMaxHeight": 2400,
                "canvasBackgroundColor": "#edeff5",
                "backgroundFxQuery": "",
                "appMode": "auto"
              },
              "pageSettings": null,
              "showViewerNavigation": true,
              "homePageId": "f105fe36-3d79-4102-bb21-629726a2f19c",
              "appId": "05231ff7-bfc1-4f9f-a090-0f0b4b69007b",
              "currentEnvironmentId": "e8aa3de4-7f32-4e5b-9624-3e8c8dc6f7e3",
              "promotedFrom": null,
              "createdAt": "2025-02-04T07:10:15.175Z",
              "updatedAt": "2025-02-04T07:10:15.159Z"
            }
          ],
          "appEnvironments": [
            {
              "id": "e8aa3de4-7f32-4e5b-9624-3e8c8dc6f7e3",
              "organizationId": "56509beb-a5fa-4361-be3b-acec5ce23a82",
              "name": "development",
              "isDefault": false,
              "priority": 1,
              "enabled": true,
              "createdAt": "2025-02-04T06:07:37.069Z",
              "updatedAt": "2025-02-04T06:07:37.069Z"
            },
            {
              "id": "fbd62148-7c6a-4ff4-8924-858ba65e645c",
              "organizationId": "56509beb-a5fa-4361-be3b-acec5ce23a82",
              "name": "staging",
              "isDefault": false,
              "priority": 2,
              "enabled": true,
              "createdAt": "2025-02-04T06:07:37.069Z",
              "updatedAt": "2025-02-04T06:07:37.069Z"
            },
            {
              "id": "eb2d123b-e5da-4e73-8b76-fbea6d075543",
              "organizationId": "56509beb-a5fa-4361-be3b-acec5ce23a82",
              "name": "production",
              "isDefault": true,
              "priority": 3,
              "enabled": true,
              "createdAt": "2025-02-04T06:07:37.069Z",
              "updatedAt": "2025-02-04T06:07:37.069Z"
            }
          ],
          "dataSourceOptions": [],
          "schemaDetails": {
            "multiPages": true,
            "multiEnv": true,
            "globalDataSources": true
          }
        }
      }
    }
  ],
  "tooljet_version": "3.0.31-ee-lts"
}